{"titulo":"\n\t\t\t\t\t\tVazamento mostra controle de fundo secreto sobre Santos e Geuvânio (23/01/16-06h00) \n\t\t\t\t\t","descricao":"","conteudo":"302 Found Found The document has moved here.","categorias":[""]}
{"titulo":"\n\t\t\t\t\t\tMenon: Palmeiras deixa boa impressão na estreia. Erik ameaça Jesus (20/01/16-22h25) \n\t\t\t\t\t","descricao":"","conteudo":"302 Found Found The document has moved here.","categorias":[""]}
{"titulo":"\n\t\t\t\t\t\tBelas de São Paulo e Vitória se exibem para você. Vote no duelo das quartas (29/11/14-06h01) \n\t\t\t\t\t","descricao":"","conteudo":"301 Moved Permanently Moved Permanently The document has moved here.","categorias":[""]}
{"titulo":"\n\t\t\t\t\t\tNão deixe de votar no duelo das Belas de Figueirense e Fortaleza (19/10/14-16h01) \n\t\t\t\t\t","descricao":"","conteudo":"301 Moved Permanently Moved Permanently The document has moved here.","categorias":[""]}
{"titulo":"\n\t\t\t\t\t\t2015 - Série B - 05/09 - Vitória x Botafogo (05/09/15-16h54) \n\t\t\t\t\t","descricao":"","conteudo":"301 Moved Permanently Moved Permanently The document has moved here.","categorias":[""]}
{"titulo":"\n\t\t\t\t\t\tJuca: No nordeste, o mais quente do futebol brasileiro hoje (29/04/15-06h55) \n\t\t\t\t\t","descricao":"","conteudo":"302 Found Found The document has moved here.","categorias":[""]}
{"titulo":"\n\t\t\t\t\t\tTécnico Dado Cavalcanti acerta com o Ceará pelo período de um ano (02/12/14-15h16) \n\t\t\t\t\t","descricao":"","conteudo":"301 Moved Permanently 301 Moved Permanently nginx","categorias":[""]}
{"titulo":"\n\t\t\t\t\t\tBlog Tênis Clube: Thiago salva (de novo) o Brasil (28/02/16-14h00) \n\t\t\t\t\t","descricao":"","conteudo":"301 Moved Permanently 301 Moved Permanently nginx","categorias":[""]}
{"titulo":"\n\t\t\t\t\t\tNishikori vence a 14ª seguida no ATP de Memphis (11/02/16-09h12) \n\t\t\t\t\t","descricao":"","conteudo":"301 Moved Permanently 301 Moved Permanently nginx","categorias":[""]}
{"titulo":"\n\t\t\t\t\t\tAssessoria até 'ensina' tênis aos jornalistas (26/02/16-20h29) \n\t\t\t\t\t","descricao":"","conteudo":"301 Moved Permanently 301 Moved Permanently nginx","categorias":[""]}
{"titulo":"\n\t\t\t\t\t\tPaula para nas quartas de duplas em Acapulco (26/02/16-12h54) \n\t\t\t\t\t","descricao":"","conteudo":"301 Moved Permanently 301 Moved Permanently nginx","categorias":[""]}
{"titulo":"\n\t\t\t\t\t\tVeja o melhor da final do Aberto Mexicano (28/02/16-12h48) \n\t\t\t\t\t","descricao":"","conteudo":"301 Moved Permanently 301 Moved Permanently nginx","categorias":[""]}
