{"titulo":"\n\t\t\t\t\t\tSandro destaca que o Ceará ainda pode subir e convoca a torcida para sábado (12/11/14-17h11) \n\t\t\t\t\t","descricao":"","conteudo":"301 Moved Permanently Moved Permanently The document has moved here.","categorias":[""]}
{"titulo":"\n\t\t\t\t\t\tSantista do 'gol perdido' também passou por calvário no Vasco. E durou anos (29/11/15-06h00) \n\t\t\t\t\t","descricao":"","conteudo":"301 Moved Permanently Moved Permanently The document has moved here.","categorias":[""]}
{"titulo":"\n\t\t\t\t\t\tMano evita polemizar expulsão de Paulo André e critica posição da defesa (27/09/15-21h15) \n\t\t\t\t\t","descricao":"","conteudo":"301 Moved Permanently Moved Permanently The document has moved here.","categorias":[""]}
{"titulo":"\n\t\t\t\t\t\tSem interesse, Fla pega Vitória em Manaus sob observação de desesperados (29/11/14-06h03) \n\t\t\t\t\t","descricao":"","conteudo":"301 Moved Permanently Moved Permanently The document has moved here.","categorias":[""]}
