{"titulo":"\n\t\t\t\t\t\tLiga Sul-Minas-Rio define tabela e terá início antes dos estaduais (26/10/15-18h45) \n\t\t\t\t\t","descricao":"","conteudo":"301 Moved Permanently Moved Permanently The document has moved here.","categorias":[""]}
{"titulo":"\n\t\t\t\t\t\tSede do Flamengo tem princípio de incêndio e fica sem luz e água (02/02/16-10h18) \n\t\t\t\t\t","descricao":"","conteudo":"301 Moved Permanently Moved Permanently The document has moved here.","categorias":[""]}
{"titulo":"\n\t\t\t\t\t\tDado Cavalcanti chega ao Ceará e pede um time mais jovem em 2015 (04/12/14-12h22) \n\t\t\t\t\t","descricao":"","conteudo":"301 Moved Permanently Moved Permanently The document has moved here.","categorias":[""]}
{"titulo":"\n\t\t\t\t\t\tAtlético-MG vence disputa com Corinthians e contrata Clayton (23/02/16-00h20) \n\t\t\t\t\t","descricao":"","conteudo":"301 Moved Permanently Moved Permanently The document has moved here.","categorias":[""]}
{"titulo":"\n\t\t\t\t\t\tCruzeiro entra no páreo com o Palmeiras por Jean (30/12/15-06h00) \n\t\t\t\t\t","descricao":"","conteudo":"301 Moved Permanently Moved Permanently The document has moved here.","categorias":[""]}
{"titulo":"\n\t\t\t\t\t\tRing girl brasileira aparece seminua e mostra o &#8216;mal&#8217; que Las Vegas faz (11/02/16-08h03) \n\t\t\t\t\t","descricao":"","conteudo":"302 Found Found The document has moved here.","categorias":[""]}
{"titulo":"\n\t\t\t\t\t\tFeliz no Ceará, Silas disputa títulos. E, um dia, quer dirigir o São Paulo (29/04/15-06h00) \n\t\t\t\t\t","descricao":"","conteudo":"302 Found Found The document has moved here.","categorias":[""]}
{"titulo":"\n\t\t\t\t\t\tFlamengo devolve meia ao Vitória após pedido do jogador (29/07/15-18h57) \n\t\t\t\t\t","descricao":"","conteudo":"301 Moved Permanently Moved Permanently The document has moved here.","categorias":[""]}
{"titulo":"\n\t\t\t\t\t\tSantos marca no fim, rebaixa Vitória e livra Palmeiras da degola (07/12/14-18h59) \n\t\t\t\t\t","descricao":"","conteudo":"301 Moved Permanently Moved Permanently The document has moved here.","categorias":[""]}
{"titulo":"\n\t\t\t\t\t\tInter vence lanterna do Gauchão por 2 a 1 em jogo com golaços (11/02/16-21h23) \n\t\t\t\t\t","descricao":"","conteudo":"301 Moved Permanently Moved Permanently The document has moved here.","categorias":[""]}
{"titulo":"\n\t\t\t\t\t\tNordeste em alta: Belas de Bahia e Santa Cruz querem te seduzir. Vote agora (21/11/14-12h01) \n\t\t\t\t\t","descricao":"","conteudo":"301 Moved Permanently Moved Permanently The document has moved here.","categorias":[""]}
{"titulo":"\n\t\t\t\t\t\tNão deixe de votar no duelo das Belas de Figueirense e Fortaleza (19/10/14-16h01) \n\t\t\t\t\t","descricao":"","conteudo":"301 Moved Permanently Moved Permanently The document has moved here.","categorias":[""]}
{"titulo":"\n\t\t\t\t\t\t2015 - Série B - 05/09 - Vitória x Botafogo (05/09/15-16h54) \n\t\t\t\t\t","descricao":"","conteudo":"301 Moved Permanently Moved Permanently The document has moved here.","categorias":[""]}
{"titulo":"\n\t\t\t\t\t\tGrêmio vence o Coritiba em jogo com lambança e apagão no estádio (07/02/16-21h38) \n\t\t\t\t\t","descricao":"","conteudo":"301 Moved Permanently Moved Permanently The document has moved here.","categorias":[""]}
{"titulo":"\n\t\t\t\t\t\tJuca: No nordeste, o mais quente do futebol brasileiro hoje (29/04/15-06h55) \n\t\t\t\t\t","descricao":"","conteudo":"302 Found Found The document has moved here.","categorias":[""]}
{"titulo":"\n\t\t\t\t\t\tBelas da Torcida voltam e animam seu Natal; veja superálbum com 280 fotos (25/12/14-06h01) \n\t\t\t\t\t","descricao":"","conteudo":"301 Moved Permanently Moved Permanently The document has moved here.","categorias":[""]}
{"titulo":"\n\t\t\t\t\t\tBellucci ganha terreno e Monteiro dá novo disparo (29/02/16-08h38) \n\t\t\t\t\t","descricao":"","conteudo":"301 Moved Permanently 301 Moved Permanently nginx","categorias":[""]}
{"titulo":"\n\t\t\t\t\t\tFeijão joga quali de challenger e confia na volta (27/02/16-21h10) \n\t\t\t\t\t","descricao":"","conteudo":"301 Moved Permanently 301 Moved Permanently nginx","categorias":[""]}
{"titulo":"\n\t\t\t\t\t\tEspanhóis terminam turnê sul-americana zerados (29/02/16-13h49) \n\t\t\t\t\t","descricao":"","conteudo":"301 Moved Permanently 301 Moved Permanently nginx","categorias":[""]}
{"titulo":"\n\t\t\t\t\t\tPaula para nas quartas de duplas em Acapulco (26/02/16-12h54) \n\t\t\t\t\t","descricao":"","conteudo":"301 Moved Permanently 301 Moved Permanently nginx","categorias":[""]}
